README.md
setup.cfg
setup.py
dr_utils/__init__.py
dr_utils/custom_functions.py
dr_utils.egg-info/PKG-INFO
dr_utils.egg-info/SOURCES.txt
dr_utils.egg-info/dependency_links.txt
dr_utils.egg-info/not-zip-safe
dr_utils.egg-info/top_level.txt