Metadata-Version: 1.0
Name: dr-utils
Version: 0.1
Summary: Custom helpers for Disaster Reponse message classifier web app.
Home-page: UNKNOWN
Author: Matthew Perkins
Author-email: UNKNOWN
License: UNKNOWN
Platform: UNKNOWN
